cyclebane/__init__.py
cyclebane/graph.py
cyclebane/node_values.py
cyclebane/py.typed
cyclebane-24.10.0.dist-info/LICENSE
cyclebane-24.10.0.dist-info/METADATA
cyclebane-24.10.0.dist-info/WHEEL
cyclebane-24.10.0.dist-info/top_level.txt
cyclebane-24.10.0.dist-info/RECORD
