Metadata-Version: 2.1
Name: cyclebane
Version: 24.10.0
Summary: Transform directed acyclic graphs using map-reduce and groupby operations
Author: Scipp contributors
License: BSD 3-Clause License
Project-URL: Bug Tracker, https://github.com/scipp/cyclebane/issues
Project-URL: Documentation, https://scipp.github.io/cyclebane
Project-URL: Source, https://github.com/scipp/cyclebane
Classifier: Intended Audience :: Science/Research
Classifier: License :: OSI Approved :: BSD License
Classifier: Natural Language :: English
Classifier: Operating System :: OS Independent
Classifier: Programming Language :: Python :: 3
Classifier: Programming Language :: Python :: 3 :: Only
Classifier: Programming Language :: Python :: 3.10
Classifier: Programming Language :: Python :: 3.11
Classifier: Programming Language :: Python :: 3.12
Classifier: Topic :: Scientific/Engineering
Classifier: Typing :: Typed
Requires-Python: >=3.10
License-File: LICENSE
Requires-Dist: networkx
